pythonjsonlogger/__init__.py
pythonjsonlogger/jsonlogger.py
chili_python_json_logger-2.1.0.dist-info/LICENSE
chili_python_json_logger-2.1.0.dist-info/METADATA
chili_python_json_logger-2.1.0.dist-info/WHEEL
chili_python_json_logger-2.1.0.dist-info/top_level.txt
chili_python_json_logger-2.1.0.dist-info/RECORD
