Metadata-Version: 2.1
Name: chili-python-json-logger
Version: 2.1.0
Summary: A python library adding a json log formatter
Home-page: https://github.com/chilispa/python-json-logger
Author: Cosimo Meli
Author-email: cosimo.meli@chili.com
License: BSD
Platform: UNKNOWN
Classifier: Development Status :: 3 - Alpha
Classifier: Intended Audience :: Developers
Classifier: License :: OSI Approved :: BSD License
Classifier: Operating System :: OS Independent
Classifier: Programming Language :: Python
Classifier: Programming Language :: Python :: 3
Classifier: Programming Language :: Python :: 3.4
Classifier: Programming Language :: Python :: 3.5
Classifier: Programming Language :: Python :: 3.6
Classifier: Programming Language :: Python :: 3.7
Classifier: Programming Language :: Python :: 3.8
Classifier: Topic :: System :: Logging
Requires-Python: >=3.4
